anchor_gpt/__init__.py
anchor_gpt/coreset.py
anchor_gpt/prompt.py
anchor_gpt/prompt_logger.py
anchor_gpt/prompt_store.py
anchor_gpt/test_logger.py
anchor_gpt-0.0.2.dist-info/LICENSE
anchor_gpt-0.0.2.dist-info/METADATA
anchor_gpt-0.0.2.dist-info/WHEEL
anchor_gpt-0.0.2.dist-info/top_level.txt
anchor_gpt-0.0.2.dist-info/RECORD
