Metadata-Version: 2.1
Name: anchor-gpt
Version: 0.0.2
Summary: Diagnose and find hallucinations in your grounded Large Language Model prompts with Anchor-GPT!
Home-page: https://github.com/dioptra-ai/anchor-gpt
Author: dioptra.ai
Author-email: info@dioptra.ai
License: BSD
Project-URL: dioptra.ai, https://www.dioptra.ai
Keywords: dioptra,anchor,gpt,hallucinations,grounding,llm
Platform: UNKNOWN
Classifier: Development Status :: 3 - Alpha
Classifier: Intended Audience :: Developers
Classifier: Programming Language :: Python :: 3.5
Classifier: Programming Language :: Python :: 3.6
Classifier: Programming Language :: Python :: 3.7
Classifier: Programming Language :: Python :: 3.8
Requires-Python: >=3.5.3
Requires-Dist: numpy
Requires-Dist: tqdm
Requires-Dist: sklearn
Requires-Dist: pandas
